setup.py
distributions_statistics_v2/Binomialdistribution.py
distributions_statistics_v2/Gaussiandistribution.py
distributions_statistics_v2/Generaldistribution.py
distributions_statistics_v2/__init__.py
distributions_statistics_v2.egg-info/PKG-INFO
distributions_statistics_v2.egg-info/SOURCES.txt
distributions_statistics_v2.egg-info/dependency_links.txt
distributions_statistics_v2.egg-info/not-zip-safe
distributions_statistics_v2.egg-info/top_level.txt