Metadata-Version: 1.0
Name: distributions-statistics-v2
Version: 0.2
Summary: Gaussian distributions
Home-page: UNKNOWN
Author: sneha
Author-email: snehaoladri96@gmail.com
License: UNKNOWN
Platform: UNKNOWN
